console/__init__.py
console/ascii4.py
console/beep.py
console/cli.py
console/color_tables.py
console/color_tables_x11.py
console/constants.py
console/core.py
console/demos.py
console/detection.py
console/disabled.py
console/meta.py
console/progress.py
console/proximity.py
console/screen.py
console/style.py
console/test_suite.py
console/utils.py
console/viewers.py
console/windows.py
console-0.9910.dist-info/LICENSE
console-0.9910.dist-info/METADATA
console-0.9910.dist-info/WHEEL
console-0.9910.dist-info/entry_points.txt
console-0.9910.dist-info/top_level.txt
console-0.9910.dist-info/RECORD
